{
  "deals": [
    {
      "origin": "SAT",
      "origin_city": "San Antonio",
      "destination": "LAS",
      "destination_city": "Las Vegas",
      "destination_country": "USA",
      "airline": "Southwest",
      "price_rt": 79,
      "price_normal": 150,
      "discount_pct": 47,
      "travel_dates": "June 10 - June 17",
      "nonstop": true,
      "deal_tier": "FLASH",
      "is_international": false,
      "booking_url": "https://www.google.com/travel/flights?q=flights+from+San+Antonio+to+Las+Vegas",
      "id": "ed894ba9-7807-44de-a74a-09903e2bfd6c",
      "is_active": true,
      "created_at": "2026-06-28T23:01:32.099Z",
      "last_seen_at": "2026-06-29T09:01:32.099Z",
      "expires_at": "2026-06-30T23:01:32.099Z"
    },
    {
      "origin": "SAT",
      "origin_city": "San Antonio",
      "destination": "ORD",
      "destination_city": "Chicago",
      "destination_country": "USA",
      "airline": "Spirit",
      "price_rt": 169,
      "price_normal": 280,
      "discount_pct": 40,
      "travel_dates": "July 5 - July 12",
      "nonstop": true,
      "deal_tier": "HOT",
      "is_international": false,
      "booking_url": "https://www.google.com/travel/flights?q=flights+from+San+Antonio+to+Chicago",
      "id": "246c9210-e700-4b31-8a0a-34904d71deea",
      "is_active": true,
      "created_at": "2026-06-28T04:01:32.099Z",
      "last_seen_at": "2026-06-29T09:01:32.099Z",
      "expires_at": "2026-06-30T04:01:32.099Z"
    },
    {
      "origin": "SAT",
      "origin_city": "San Antonio",
      "destination": "MIA",
      "destination_city": "Miami",
      "destination_country": "USA",
      "airline": "American",
      "price_rt": 129,
      "price_normal": 220,
      "discount_pct": 41,
      "travel_dates": "June 15 - June 22",
      "nonstop": true,
      "deal_tier": "FLASH",
      "is_international": false,
      "booking_url": "https://www.google.com/travel/flights?q=flights+from+San+Antonio+to+Miami",
      "id": "1795c755-fcda-4e43-9e74-6fa7a316a368",
      "is_active": true,
      "created_at": "2026-06-29T02:01:32.099Z",
      "last_seen_at": "2026-06-29T09:01:32.099Z",
      "expires_at": "2026-07-01T02:01:32.099Z"
    },
    {
      "origin": "SAT",
      "origin_city": "San Antonio",
      "destination": "DEN",
      "destination_city": "Denver",
      "destination_country": "USA",
      "airline": "Frontier",
      "price_rt": 89,
      "price_normal": 170,
      "discount_pct": 48,
      "travel_dates": "July 10 - July 17",
      "nonstop": true,
      "deal_tier": "FLASH",
      "is_international": false,
      "booking_url": "https://www.google.com/travel/flights?q=flights+from+San+Antonio+to+Denver",
      "id": "919e4be9-8fec-43df-bfd9-b936d648a338",
      "is_active": true,
      "created_at": "2026-06-29T01:01:32.099Z",
      "last_seen_at": "2026-06-29T09:01:32.099Z",
      "expires_at": "2026-07-01T01:01:32.099Z"
    },
    {
      "origin": "SAT",
      "origin_city": "San Antonio",
      "destination": "LAS",
      "destination_city": "Las Vegas",
      "destination_country": "USA",
      "airline": "Spirit",
      "price_rt": 69,
      "price_normal": 140,
      "discount_pct": 51,
      "travel_dates": "June 20 - June 27",
      "nonstop": true,
      "deal_tier": "FLASH",
      "is_international": false,
      "booking_url": "https://www.google.com/travel/flights?q=flights+from+San+Antonio+to+Las+Vegas",
      "id": "57a9819e-c171-4ffb-9da5-37aa7d7ee9c6",
      "is_active": true,
      "created_at": "2026-06-29T08:01:32.099Z",
      "last_seen_at": "2026-06-29T09:01:32.099Z",
      "expires_at": "2026-07-01T08:01:32.099Z"
    },
    {
      "origin": "SAT",
      "origin_city": "San Antonio",
      "destination": "CUN",
      "destination_city": "Cancun",
      "destination_country": "Mexico",
      "airline": "Volaris",
      "price_rt": 219,
      "price_normal": 400,
      "discount_pct": 45,
      "travel_dates": "July 1 - July 8",
      "nonstop": true,
      "deal_tier": "HOT",
      "is_international": true,
      "booking_url": "https://www.google.com/travel/flights?q=flights+from+San+Antonio+to+Cancun",
      "id": "ad4d2537-9686-4647-b9f7-bff1b51beeed",
      "is_active": true,
      "created_at": "2026-06-28T02:01:32.099Z",
      "last_seen_at": "2026-06-29T09:01:32.099Z",
      "expires_at": "2026-06-30T02:01:32.099Z"
    },
    {
      "origin": "SAT",
      "origin_city": "San Antonio",
      "destination": "GDL",
      "destination_city": "Guadalajara",
      "destination_country": "Mexico",
      "airline": "Volaris",
      "price_rt": 119,
      "price_normal": 250,
      "discount_pct": 52,
      "travel_dates": "June 25 - July 2",
      "nonstop": true,
      "deal_tier": "FLASH",
      "is_international": true,
      "booking_url": "https://www.google.com/travel/flights?q=flights+from+San+Antonio+to+Guadalajara",
      "id": "f7084977-b5a6-40c8-8739-70ed40d0abc3",
      "is_active": true,
      "created_at": "2026-06-28T16:01:32.099Z",
      "last_seen_at": "2026-06-29T09:01:32.099Z",
      "expires_at": "2026-06-30T16:01:32.099Z"
    },
    {
      "origin": "SAT",
      "origin_city": "San Antonio",
      "destination": "MCO",
      "destination_city": "Orlando",
      "destination_country": "USA",
      "airline": "Southwest",
      "price_rt": 149,
      "price_normal": 220,
      "discount_pct": 32,
      "travel_dates": "July 15 - July 22",
      "nonstop": true,
      "deal_tier": "HOT",
      "is_international": false,
      "booking_url": "https://www.google.com/travel/flights?q=flights+from+San+Antonio+to+Orlando",
      "id": "9ea39f2b-e21b-4dbd-9cd5-3de5373e2335",
      "is_active": true,
      "created_at": "2026-06-27T17:01:32.099Z",
      "last_seen_at": "2026-06-29T09:01:32.099Z",
      "expires_at": "2026-06-29T17:01:32.099Z"
    },
    {
      "origin": "SAT",
      "origin_city": "San Antonio",
      "destination": "PHX",
      "destination_city": "Phoenix",
      "destination_country": "USA",
      "airline": "Frontier",
      "price_rt": 99,
      "price_normal": 180,
      "discount_pct": 45,
      "travel_dates": "June 5 - June 12",
      "nonstop": true,
      "deal_tier": "HOT",
      "is_international": false,
      "booking_url": "https://www.google.com/travel/flights?q=flights+from+San+Antonio+to+Phoenix",
      "id": "50bf0da5-18ef-48cf-a9a1-695ef23c3ccb",
      "is_active": true,
      "created_at": "2026-06-27T21:01:32.099Z",
      "last_seen_at": "2026-06-29T09:01:32.099Z",
      "expires_at": "2026-06-29T21:01:32.099Z"
    },
    {
      "origin": "SAT",
      "origin_city": "San Antonio",
      "destination": "ATL",
      "destination_city": "Atlanta",
      "destination_country": "USA",
      "airline": "Spirit",
      "price_rt": 139,
      "price_normal": 220,
      "discount_pct": 37,
      "travel_dates": "July 20 - July 27",
      "nonstop": true,
      "deal_tier": "HOT",
      "is_international": false,
      "booking_url": "https://www.google.com/travel/flights?q=flights+from+San+Antonio+to+Atlanta",
      "id": "74210efd-8447-4325-9b2f-23abb23fc6f3",
      "is_active": true,
      "created_at": "2026-06-28T03:01:32.099Z",
      "last_seen_at": "2026-06-29T09:01:32.099Z",
      "expires_at": "2026-06-30T03:01:32.099Z"
    },
    {
      "origin": "AUS",
      "origin_city": "Austin",
      "destination": "DEN",
      "destination_city": "Denver",
      "destination_country": "USA",
      "airline": "Southwest",
      "price_rt": 89,
      "price_normal": 160,
      "discount_pct": 44,
      "travel_dates": "June 12 - June 19",
      "nonstop": true,
      "deal_tier": "FLASH",
      "is_international": false,
      "booking_url": "https://www.google.com/travel/flights?q=flights+from+Austin+to+Denver",
      "id": "a770773f-64b4-4dd7-9de0-cade89606249",
      "is_active": true,
      "created_at": "2026-06-28T22:01:32.099Z",
      "last_seen_at": "2026-06-29T09:01:32.099Z",
      "expires_at": "2026-06-30T22:01:32.099Z"
    },
    {
      "origin": "AUS",
      "origin_city": "Austin",
      "destination": "JFK",
      "destination_city": "New York",
      "destination_country": "USA",
      "airline": "American",
      "price_rt": 189,
      "price_normal": 320,
      "discount_pct": 41,
      "travel_dates": "July 8 - July 15",
      "nonstop": true,
      "deal_tier": "HOT",
      "is_international": false,
      "booking_url": "https://www.google.com/travel/flights?q=flights+from+Austin+to+New+York",
      "id": "86b408dc-65e9-4868-8714-fdf4f55fffe9",
      "is_active": true,
      "created_at": "2026-06-27T17:01:32.099Z",
      "last_seen_at": "2026-06-29T09:01:32.099Z",
      "expires_at": "2026-06-29T17:01:32.099Z"
    },
    {
      "origin": "AUS",
      "origin_city": "Austin",
      "destination": "LAX",
      "destination_city": "Los Angeles",
      "destination_country": "USA",
      "airline": "American",
      "price_rt": 159,
      "price_normal": 240,
      "discount_pct": 34,
      "travel_dates": "June 18 - June 25",
      "nonstop": true,
      "deal_tier": "HOT",
      "is_international": false,
      "booking_url": "https://www.google.com/travel/flights?q=flights+from+Austin+to+Los+Angeles",
      "id": "588348d3-774f-4308-8077-d96b62765f6b",
      "is_active": true,
      "created_at": "2026-06-27T19:01:32.099Z",
      "last_seen_at": "2026-06-29T09:01:32.099Z",
      "expires_at": "2026-06-29T19:01:32.099Z"
    },
    {
      "origin": "AUS",
      "origin_city": "Austin",
      "destination": "MIA",
      "destination_city": "Miami",
      "destination_country": "USA",
      "airline": "American",
      "price_rt": 139,
      "price_normal": 220,
      "discount_pct": 37,
      "travel_dates": "July 10 - July 17",
      "nonstop": true,
      "deal_tier": "HOT",
      "is_international": false,
      "booking_url": "https://www.google.com/travel/flights?q=flights+from+Austin+to+Miami",
      "id": "8aff999c-8af6-465a-81ae-ae1430b77f86",
      "is_active": true,
      "created_at": "2026-06-27T17:01:32.099Z",
      "last_seen_at": "2026-06-29T09:01:32.099Z",
      "expires_at": "2026-06-29T17:01:32.099Z"
    },
    {
      "origin": "AUS",
      "origin_city": "Austin",
      "destination": "ORD",
      "destination_city": "Chicago",
      "destination_country": "USA",
      "airline": "American",
      "price_rt": 179,
      "price_normal": 260,
      "discount_pct": 31,
      "travel_dates": "June 22 - June 29",
      "nonstop": true,
      "deal_tier": "HOT",
      "is_international": false,
      "booking_url": "https://www.google.com/travel/flights?q=flights+from+Austin+to+Chicago",
      "id": "9b07220a-f349-4919-923d-1d2b3c016b42",
      "is_active": true,
      "created_at": "2026-06-29T00:01:32.099Z",
      "last_seen_at": "2026-06-29T09:01:32.099Z",
      "expires_at": "2026-07-01T00:01:32.099Z"
    },
    {
      "origin": "AUS",
      "origin_city": "Austin",
      "destination": "PHX",
      "destination_city": "Phoenix",
      "destination_country": "USA",
      "airline": "Southwest",
      "price_rt": 109,
      "price_normal": 180,
      "discount_pct": 39,
      "travel_dates": "July 3 - July 10",
      "nonstop": true,
      "deal_tier": "HOT",
      "is_international": false,
      "booking_url": "https://www.google.com/travel/flights?q=flights+from+Austin+to+Phoenix",
      "id": "36f39ac1-b5c0-4bda-a4fd-ca2a8e658d74",
      "is_active": true,
      "created_at": "2026-06-29T06:01:32.099Z",
      "last_seen_at": "2026-06-29T09:01:32.099Z",
      "expires_at": "2026-07-01T06:01:32.099Z"
    },
    {
      "origin": "AUS",
      "origin_city": "Austin",
      "destination": "LAS",
      "destination_city": "Las Vegas",
      "destination_country": "USA",
      "airline": "Southwest",
      "price_rt": 129,
      "price_normal": 200,
      "discount_pct": 35,
      "travel_dates": "June 28 - July 5",
      "nonstop": true,
      "deal_tier": "HOT",
      "is_international": false,
      "booking_url": "https://www.google.com/travel/flights?q=flights+from+Austin+to+Las+Vegas",
      "id": "9f2e4bb3-888b-469c-a2e6-f26ecfb8100a",
      "is_active": true,
      "created_at": "2026-06-27T18:01:32.099Z",
      "last_seen_at": "2026-06-29T09:01:32.099Z",
      "expires_at": "2026-06-29T18:01:32.099Z"
    },
    {
      "origin": "AUS",
      "origin_city": "Austin",
      "destination": "ATL",
      "destination_city": "Atlanta",
      "destination_country": "USA",
      "airline": "Delta",
      "price_rt": 159,
      "price_normal": 240,
      "discount_pct": 34,
      "travel_dates": "July 15 - July 22",
      "nonstop": true,
      "deal_tier": "HOT",
      "is_international": false,
      "booking_url": "https://www.google.com/travel/flights?q=flights+from+Austin+to+Atlanta",
      "id": "a04415da-ef6d-4f8d-bfff-0d3131397638",
      "is_active": true,
      "created_at": "2026-06-27T23:01:32.099Z",
      "last_seen_at": "2026-06-29T09:01:32.099Z",
      "expires_at": "2026-06-29T23:01:32.099Z"
    },
    {
      "origin": "IAH",
      "origin_city": "Houston",
      "destination": "SJU",
      "destination_city": "San Juan",
      "destination_country": "Puerto Rico",
      "airline": "United",
      "price_rt": 219,
      "price_normal": 380,
      "discount_pct": 42,
      "travel_dates": "June 10 - June 17",
      "nonstop": true,
      "deal_tier": "HOT",
      "is_international": true,
      "booking_url": "https://www.google.com/travel/flights?q=flights+from+Houston+to+San+Juan",
      "id": "ee302e98-c72f-4333-a5d7-237fa6870d46",
      "is_active": true,
      "created_at": "2026-06-28T16:01:32.099Z",
      "last_seen_at": "2026-06-29T09:01:32.099Z",
      "expires_at": "2026-06-30T16:01:32.099Z"
    },
    {
      "origin": "IAH",
      "origin_city": "Houston",
      "destination": "MEX",
      "destination_city": "Mexico City",
      "destination_country": "Mexico",
      "airline": "Aeromexico",
      "price_rt": 149,
      "price_normal": 270,
      "discount_pct": 45,
      "travel_dates": "July 5 - July 12",
      "nonstop": true,
      "deal_tier": "FLASH",
      "is_international": true,
      "booking_url": "https://www.google.com/travel/flights?q=flights+from+Houston+to+Mexico+City",
      "id": "6eed2902-760f-4527-bcf2-34d7afbbb850",
      "is_active": true,
      "created_at": "2026-06-29T02:01:32.099Z",
      "last_seen_at": "2026-06-29T09:01:32.099Z",
      "expires_at": "2026-07-01T02:01:32.099Z"
    },
    {
      "origin": "IAH",
      "origin_city": "Houston",
      "destination": "GDL",
      "destination_city": "Guadalajara",
      "destination_country": "Mexico",
      "airline": "Aeromexico",
      "price_rt": 169,
      "price_normal": 280,
      "discount_pct": 40,
      "travel_dates": "June 15 - June 22",
      "nonstop": true,
      "deal_tier": "HOT",
      "is_international": true,
      "booking_url": "https://www.google.com/travel/flights?q=flights+from+Houston+to+Guadalajara",
      "id": "0885889b-7212-432a-b4b5-fed9663647ea",
      "is_active": true,
      "created_at": "2026-06-29T08:01:32.099Z",
      "last_seen_at": "2026-06-29T09:01:32.099Z",
      "expires_at": "2026-07-01T08:01:32.099Z"
    },
    {
      "origin": "IAH",
      "origin_city": "Houston",
      "destination": "MTY",
      "destination_city": "Monterrey",
      "destination_country": "Mexico",
      "airline": "Aeromexico",
      "price_rt": 159,
      "price_normal": 260,
      "discount_pct": 39,
      "travel_dates": "July 10 - July 17",
      "nonstop": true,
      "deal_tier": "HOT",
      "is_international": true,
      "booking_url": "https://www.google.com/travel/flights?q=flights+from+Houston+to+Monterrey",
      "id": "59ccac4b-3f0d-4673-9661-0877f86c21d9",
      "is_active": true,
      "created_at": "2026-06-27T17:01:32.099Z",
      "last_seen_at": "2026-06-29T09:01:32.099Z",
      "expires_at": "2026-06-29T17:01:32.099Z"
    },
    {
      "origin": "IAH",
      "origin_city": "Houston",
      "destination": "CUN",
      "destination_city": "Cancun",
      "destination_country": "Mexico",
      "airline": "Aeromexico",
      "price_rt": 199,
      "price_normal": 350,
      "discount_pct": 43,
      "travel_dates": "June 20 - June 27",
      "nonstop": true,
      "deal_tier": "HOT",
      "is_international": true,
      "booking_url": "https://www.google.com/travel/flights?q=flights+from+Houston+to+Cancun",
      "id": "fa0f49fb-bc94-4cd2-920b-07fe6e754532",
      "is_active": true,
      "created_at": "2026-06-27T20:01:32.099Z",
      "last_seen_at": "2026-06-29T09:01:32.099Z",
      "expires_at": "2026-06-29T20:01:32.099Z"
    },
    {
      "origin": "HOU",
      "origin_city": "Houston",
      "destination": "MIA",
      "destination_city": "Miami",
      "destination_country": "USA",
      "airline": "Southwest",
      "price_rt": 119,
      "price_normal": 220,
      "discount_pct": 46,
      "travel_dates": "July 1 - July 8",
      "nonstop": false,
      "deal_tier": "FLASH",
      "is_international": false,
      "booking_url": "https://www.google.com/travel/flights?q=flights+from+Houston+to+Miami",
      "id": "8937f1c6-65cd-4a3b-93c7-2d35b62ad0de",
      "is_active": true,
      "created_at": "2026-06-27T20:01:32.099Z",
      "last_seen_at": "2026-06-29T09:01:32.099Z",
      "expires_at": "2026-06-29T20:01:32.099Z"
    },
    {
      "origin": "HOU",
      "origin_city": "Houston",
      "destination": "DEN",
      "destination_city": "Denver",
      "destination_country": "USA",
      "airline": "Southwest",
      "price_rt": 99,
      "price_normal": 180,
      "discount_pct": 45,
      "travel_dates": "June 25 - July 2",
      "nonstop": true,
      "deal_tier": "HOT",
      "is_international": false,
      "booking_url": "https://www.google.com/travel/flights?q=flights+from+Houston+to+Denver",
      "id": "cb31cac0-4e36-4e32-bf09-03c3846a31a0",
      "is_active": true,
      "created_at": "2026-06-28T23:01:32.099Z",
      "last_seen_at": "2026-06-29T09:01:32.099Z",
      "expires_at": "2026-06-30T23:01:32.099Z"
    },
    {
      "origin": "HOU",
      "origin_city": "Houston",
      "destination": "LAS",
      "destination_city": "Las Vegas",
      "destination_country": "USA",
      "airline": "Southwest",
      "price_rt": 89,
      "price_normal": 160,
      "discount_pct": 44,
      "travel_dates": "July 15 - July 22",
      "nonstop": true,
      "deal_tier": "HOT",
      "is_international": false,
      "booking_url": "https://www.google.com/travel/flights?q=flights+from+Houston+to+Las+Vegas",
      "id": "058c44e6-8fdd-4cab-9550-f250b9f8f786",
      "is_active": true,
      "created_at": "2026-06-29T00:01:32.099Z",
      "last_seen_at": "2026-06-29T09:01:32.099Z",
      "expires_at": "2026-07-01T00:01:32.099Z"
    },
    {
      "origin": "HOU",
      "origin_city": "Houston",
      "destination": "PHX",
      "destination_city": "Phoenix",
      "destination_country": "USA",
      "airline": "Southwest",
      "price_rt": 109,
      "price_normal": 180,
      "discount_pct": 39,
      "travel_dates": "June 5 - June 12",
      "nonstop": true,
      "deal_tier": "HOT",
      "is_international": false,
      "booking_url": "https://www.google.com/travel/flights?q=flights+from+Houston+to+Phoenix",
      "id": "3e39ef6b-8808-4200-a88f-8f1e238e304f",
      "is_active": true,
      "created_at": "2026-06-27T20:01:32.099Z",
      "last_seen_at": "2026-06-29T09:01:32.099Z",
      "expires_at": "2026-06-29T20:01:32.099Z"
    },
    {
      "origin": "HOU",
      "origin_city": "Houston",
      "destination": "ATL",
      "destination_city": "Atlanta",
      "destination_country": "USA",
      "airline": "Southwest",
      "price_rt": 139,
      "price_normal": 220,
      "discount_pct": 37,
      "travel_dates": "July 20 - July 27",
      "nonstop": false,
      "deal_tier": "HOT",
      "is_international": false,
      "booking_url": "https://www.google.com/travel/flights?q=flights+from+Houston+to+Atlanta",
      "id": "0bb0387c-1666-4f6c-ba9c-dc29180b0003",
      "is_active": true,
      "created_at": "2026-06-28T04:01:32.099Z",
      "last_seen_at": "2026-06-29T09:01:32.099Z",
      "expires_at": "2026-06-30T04:01:32.099Z"
    }
  ],
  "generated_at": "2026-06-29T09:01:32.100Z",
  "total": 28,
  "version": "2.0",
  "scan_duration_ms": 27265
}